Workbook

Sheet Summary
A1: NIKE, Inc. (NYSE: NKE) - DCF & Comparable Company Valuation
A2: Independent project. $ in millions except per share. Market data as of Oct 9, 2026. Scenario switch: Assumptions!B3.
A4: Current share price | B4: =Assumptions!B5 -> 34.71
A5: WACC | B5: =Assumptions!B21 -> 0.09663292
A6: Terminal growth | B6: =Assumptions!B27 -> 0.03
A7: DCF value per share (selected scenario) | B7: =DCF!B29 -> 35.174192
A8: Upside / (downside) | B8: =DCF!B30 -> 0.01337345
A9: Terminal value % of EV | B9: =DCF!B31 -> 0.79466275
A10: Exit-multiple cross-check ($/share, 12.0x) | B10: =DCF!B41 -> 40.74439
A11: Comps median-implied value ($/share) | B11: =Comps!E22 -> 31.380546
A12: Downside / Base / Upside DCF ($/share) | B12: $24.13 / $35.17 / $44.77
A13: Probability-weighted DCF (25/50/25) | B13: 34.812643
A15: Conclusion
A16: HOLD. The base-case DCF ($35.17) is within 2% of the $34.71 price, so the market already prices in a margin recovery from 8.2% to about 11% by FY2031. Downside (margins stall near 8%) is $24.13 (-30%) and upside (margins return to 13.5%) is $44.77 (+29%), roughly symmetric; the probability-weighted value is $34.81. About 79% of EV sits in the terminal value, so the call depends on the margin recovery and on WACC (+/-50bp of WACC moves value by about $2.5-3 per share). Comps imply about $31 at the median peer multiple. Would turn Buy below roughly $29 (about 20% upside to base) or on evidence of gross-margin recovery; key risks are tariffs, China, and wholesale/DTC mix.

Sheet Assumptions
A1: NIKE (NKE) - DCF Assumptions ($ in millions, except per share)
A2: Blue = input. Fiscal year ends May 31. Valuation date Oct 10, 2026 (prices as of Oct 9, 2026 close). Scenario: 1=Base, 2=Downside, 3=Upside.
A3: Scenario (1/2/3) | B3: 1
A4: MARKET & BALANCE SHEET
A5: Share price ($) | B5: 34.71
A6: Diluted shares (mm) | B6: 1480
A7: Market cap | B7: 51364.2
A8: Total debt (LT $5,942 + current $2,000) | B8: 7942
A9: Cash + short-term investments ($7,563 + $1,464) | B9: 9027
A10: FY2026 revenue | B10: 46398
A12: COST OF CAPITAL
A13: Risk-free rate (10Y UST, Oct 9, 2026) | B13: 0.0524
A14: Equity risk premium (assumption) | B14: 0.05
A15: Beta (60-month regression vs SPY) | B15: 1.04
A16: Cost of equity | B16: =B13+B15*B14 -> 0.1044
A17: Pre-tax cost of debt (assumption) | B17: 0.058
A18: Tax rate | B18: 0.2
A19: Equity weight | B19: =B7/(B7+B8) -> 0.86608483
A20: Debt weight | B20: =1-B19 -> 0.13391517
A21: WACC | B21: =B16*B19+B17*(1-B18)*B20 -> 0.09663292
A23: OPERATING & TERMINAL
A24: D&A (% revenue) | B24: 0.0161
A25: Capex (% revenue) | B25: 0.018
A26: Change in NWC (% of change in revenue) | B26: 0.1
A27: Terminal growth rate | B27: 0.03
A28: Stub: fraction of FY2027 remaining at valuation date | B28: 0.64
A29: Exit multiple cross-check (EV/EBITDA) | B29: 12
A31: Operating cases | B31: FY2027E | C31: FY2028E | D31: FY2029E | E31: FY2030E | F31: FY2031E
A32: Revenue growth - Base | B32: -0.0749 | C32: 0.0043 | D32: 0.04 | E32: 0.05 | F32: 0.05
A33: EBIT margin - Base | B33: 0.056 | C33: 0.066 | D33: 0.085 | E33: 0.1 | F33: 0.11
A34: Revenue growth - Downside | B34: -0.0749 | C34: -0.02 | D34: 0.01 | E34: 0.02 | F34: 0.03
A35: EBIT margin - Downside | B35: 0.056 | C35: 0.055 | D35: 0.065 | E35: 0.075 | F35: 0.08
A36: Revenue growth - Upside | B36: -0.0749 | C36: 0.01 | D36: 0.06 | E36: 0.07 | F36: 0.07
A37: EBIT margin - Upside | B37: 0.056 | C37: 0.07 | D37: 0.1 | E37: 0.12 | F37: 0.135
A39: Notes: FY2027 and FY2028 revenue use consensus ($42.9B, $43.1B); FY2027-28 EBIT margins are derived from consensus EBITDA less D&A (5.6% and 6.6%). FY2026 EBIT margin was 8.2% vs 12.3% in FY2024. Base case assumes a gradual recovery to 11% by FY2031. Cost of debt, ERP, terminal growth and the outer-year recovery path are my assumptions.

Sheet DCF
A1: NIKE - Discounted Cash Flow ($ in millions)
B3: FY2026A | C3: FY2027E | D3: FY2028E | E3: FY2029E | F3: FY2030E | G3: FY2031E
A4: Revenue | B4: =Assumptions!B10 -> 46398 | C4: =B4*(1+C5) -> 42922.79 | D4: =C4*(1+D5) -> 43107.358 | E4: =D4*(1+E5) -> 44831.652 | F4: =E4*(1+F5) -> 47073.235 | G4: =F4*(1+G5) -> 49426.896
A5: growth % | C5: =CHOOSE(Assumptions!$B$3,Assumptions!B32,Assumptions!B34,Assumptions!B36) -> -0.0749 | D5: =CHOOSE(Assumptions!$B$3,Assumptions!C32,Assumptions!C34,Assumptions!C36) -> 0.0043 | E5: =CHOOSE(Assumptions!$B$3,Assumptions!D32,Assumptions!D34,Assumptions!D36) -> 0.04 | F5: =CHOOSE(Assumptions!$B$3,Assumptions!E32,Assumptions!E34,Assumptions!E36) -> 0.05 | G5: =CHOOSE(Assumptions!$B$3,Assumptions!F32,Assumptions!F34,Assumptions!F36) -> 0.05
A6: EBIT margin % | C6: =CHOOSE(Assumptions!$B$3,Assumptions!B33,Assumptions!B35,Assumptions!B37) -> 0.056 | D6: =CHOOSE(Assumptions!$B$3,Assumptions!C33,Assumptions!C35,Assumptions!C37) -> 0.066 | E6: =CHOOSE(Assumptions!$B$3,Assumptions!D33,Assumptions!D35,Assumptions!D37) -> 0.085 | F6: =CHOOSE(Assumptions!$B$3,Assumptions!E33,Assumptions!E35,Assumptions!E37) -> 0.1 | G6: =CHOOSE(Assumptions!$B$3,Assumptions!F33,Assumptions!F35,Assumptions!F37) -> 0.11
A7: EBIT | C7: =C4*C6 -> 2403.6762 | D7: =D4*D6 -> 2845.0856 | E7: =E4*E6 -> 3810.6904 | F7: =F4*F6 -> 4707.3235 | G7: =G4*G6 -> 5436.9586
A8: Less: taxes | C8: =-C7*Assumptions!$B$18 -> -480.73525 | D8: =-D7*Assumptions!$B$18 -> -569.01712 | E8: =-E7*Assumptions!$B$18 -> -762.13809 | F8: =-F7*Assumptions!$B$18 -> -941.46469 | G8: =-G7*Assumptions!$B$18 -> -1087.3917
A9: NOPAT | C9: =C7+C8 -> 1922.941 | D9: =D7+D8 -> 2276.0685 | E9: =E7+E8 -> 3048.5523 | F9: =F7+F8 -> 3765.8588 | G9: =G7+G8 -> 4349.5669
A10: Plus: D&A | C10: =C4*Assumptions!$B$24 -> 691.05692 | D10: =D4*Assumptions!$B$24 -> 694.02846 | E10: =E4*Assumptions!$B$24 -> 721.7896 | F10: =F4*Assumptions!$B$24 -> 757.87908 | G10: =G4*Assumptions!$B$24 -> 795.77303
A11: Less: capex | C11: =-C4*Assumptions!$B$25 -> -772.61022 | D11: =-D4*Assumptions!$B$25 -> -775.93244 | E11: =-E4*Assumptions!$B$25 -> -806.96974 | F11: =-F4*Assumptions!$B$25 -> -847.31822 | G11: =-G4*Assumptions!$B$25 -> -889.68414
A12: Less: increase in NWC | C12: =-(C4-B4)*Assumptions!$B$26 -> 347.52102 | D12: =-(D4-C4)*Assumptions!$B$26 -> -18.4568 | E12: =-(E4-D4)*Assumptions!$B$26 -> -172.42943 | F12: =-(F4-E4)*Assumptions!$B$26 -> -224.15826 | G12: =-(G4-F4)*Assumptions!$B$26 -> -235.36617
A13: Unlevered FCF | C13: =C9+C10+C11+C12 -> 2188.9087 | D13: =D9+D10+D11+D12 -> 2175.7077 | E13: =E9+E10+E11+E12 -> 2790.9428 | F13: =F9+F10+F11+F12 -> 3452.2614 | G13: =G9+G10+G11+G12 -> 4020.2896
A14: Fraction of year counted | C14: =Assumptions!$B$28 -> 0.64 | D14: 1 | E14: 1 | F14: 1 | G14: 1
A15: FCF counted | C15: =C13*C14 -> 1400.9016 | D15: =D13*D14 -> 2175.7077 | E15: =E13*E14 -> 2790.9428 | F15: =F13*F14 -> 3452.2614 | G15: =G13*G14 -> 4020.2896
A16: Discount period (years) | C16: =Assumptions!$B$28 -> 0.64 | D16: =C16+1 -> 1.64 | E16: =D16+1 -> 2.64 | F16: =E16+1 -> 3.64 | G16: =F16+1 -> 4.64
A17: Discount factor | C17: =1/(1+Assumptions!$B$21)^C16 -> 0.94267238 | D17: =1/(1+Assumptions!$B$21)^D16 -> 0.85960613 | E17: =1/(1+Assumptions!$B$21)^E16 -> 0.7838595 | F17: =1/(1+Assumptions!$B$21)^F16 -> 0.71478749 | G17: =1/(1+Assumptions!$B$21)^G16 -> 0.65180197
A18: PV of FCF | C18: =C15*C17 -> 1320.5912 | D18: =D15*D17 -> 1870.2517 | E18: =E15*E17 -> 2187.707 | F18: =F15*F17 -> 2467.6333 | G18: =G15*G17 -> 2620.4327
A20: Valuation (perpetuity growth) | B20: Value
A21: Sum of PV of FCF | B21: =SUM(C18:G18) -> 10466.616
A22: Terminal value (FY2031 FCF x (1+g) / (WACC - g)) | B22: =G13*(1+Assumptions!B27)/(Assumptions!B21-Assumptions!B27) -> 62144.932
A23: PV of terminal value | B23: =B22/(1+Assumptions!B21)^G16 -> 40506.189
A24: Enterprise value | B24: =B21+B23 -> 50972.805
A25: Less: debt | B25: =-Assumptions!B8 -> -7942
A26: Plus: cash & ST investments | B26: =Assumptions!B9 -> 9027
A27: Equity value | B27: =SUM(B24:B26) -> 52057.805
A28: Diluted shares (mm) | B28: =Assumptions!B6 -> 1480
A29: Implied value per share ($) | B29: =B27/B28 -> 35.174192
A30: Upside / (downside) vs current | B30: =B29/Assumptions!B5-1 -> 0.01337345
A31: Terminal value % of EV | B31: =B23/B24 -> 0.79466275
A32: Implied terminal EV/EBITDA | B32: =B22/(G7+G10) -> 9.9707377
A34: Cross-check: exit multiple method | B34: Value
A35: FY2031 EBITDA | B35: =G7+G10 -> 6232.7316
A36: Exit EV/EBITDA | B36: =Assumptions!B29 -> 12
A37: Terminal value | B37: =B35*B36 -> 74792.78
A38: PV of terminal value | B38: =B37/(1+Assumptions!B21)^G16 -> 48750.081
A39: Enterprise value | B39: =B21+B38 -> 59216.697
A40: Equity value | B40: =B39+B25+B26 -> 60301.697
A41: Implied value per share ($) | B41: =B40/B28 -> 40.74439

Sheet Comps
A1: Comparable companies - EV/EBITDA and EV/Sales at each company's latest fiscal year-end
A2: Caution: multiples are at fiscal year-end dates (some are 6-12 months old) because only annual ratio data was available; refresh with current prices before relying on them.
A4: Company | B4: Ticker | C4: Fiscal year-end | D4: EV/EBITDA | E4: EV/Sales | F4: Included?
A5: Lululemon | B5: LULU | C5: 2026-02-01 | D5: 7.507 | E5: 1.83 | F5: Yes
A6: Deckers | B6: DECK | C6: 2026-03-31 | D6: 9.306 | E6: 2.28 | F6: Yes
A7: V.F. Corp | B7: VFC | C7: 2026-03-28 | D7: 8.731 | E7: 1.102 | F7: Yes
A8: Columbia Sportswear | B8: COLM | C8: 2025-12-31 | D8: 9.982 | E8: 0.775 | F8: Yes
A9: Birkenstock | B9: BIRK | C9: 2025-09-30 | D9: 12.216 | E9: 3.862 | F9: Yes
A10: On Holding | B10: ONON | C10: 2025-12-31 | D10: 23.099 | E10: 3.866 | F10: Yes
A11: Amer Sports | B11: AS | C11: 2025-12-31 | D11: 20.211 | E11: 3.343 | F11: Yes
A12: Excluded: Crocs (FY2025 EV/EBITDA of 25.2x distorted by write-downs), Under Armour (negative EBITDA), adidas and PUMA (no ratio data pulled).
A14: 25th percentile EV/EBITDA | D14: =QUARTILE(D5:D11,1) -> 9.0185
A15: Median EV/EBITDA | D15: =MEDIAN(D5:D11) -> 9.982
A16: 75th percentile EV/EBITDA | D16: =QUARTILE(D5:D11,3) -> 16.2135
A18: NKE FY2026 EBITDA (EBIT $3,797 + D&A $747) | D18: =3797+747 -> 4544
A19: NKE current EV / FY2026 EBITDA | D19: =(Assumptions!B7+Assumptions!B8-Assumptions!B9)/D18 -> 11.064965
A21: Implied NKE value per share | D21: Low (25th pct) | E21: Median | F21: High (75th pct)
A22: EV/EBITDA x FY2026 EBITDA | D22: =(D14*$D$18-Assumptions!$B$8+Assumptions!$B$9)/Assumptions!$B$6 -> 28.422341 | E22: =(D15*$D$18-Assumptions!$B$8+Assumptions!$B$9)/Assumptions!$B$6 -> 31.380546 | F22: =(D16*$D$18-Assumptions!$B$8+Assumptions!$B$9)/Assumptions!$B$6 -> 50.512935

Sheet Sensitivities
A1: Sensitivity analysis (static values computed by a Python replica verified against the live DCF at base inputs)
A3: Base case value per share ($): WACC (rows) vs terminal growth (columns)
A4: WACC \ g | B4: 2.0% | C4: 2.5% | D4: 3.0% | E4: 3.5% | F4: 4.0%
A5: 8.66% | B5: 36.27932 | C5: 38.72344 | D5: 41.599132 | E5: 45.031773 | F5: 49.200512
A6: 9.16% | B6: 33.652918 | C6: 35.720988 | D6: 38.124604 | E6: 40.952641 | F6: 44.328397
A7: 9.66% | B7: 31.3717 | C7: 33.140239 | D7: 35.174192 | E7: 37.538157 | F7: 40.319541
A8: 10.16% | B8: 29.372187 | C8: 30.898595 | D8: 32.638091 | E8: 34.638642 | F8: 36.963786
A9: 10.66% | B9: 27.605558 | C9: 28.933699 | D9: 30.435153 | E9: 32.14621 | F9: 34.114056
A11: Scenario summary
A12: Scenario | B12: Value/share | C12: vs $34.71 | D12: FY31 EBIT margin | E12: TV % of EV | F12: Weight
A13: Downside | B13: 24.132036 | C13: -0.30475265 | D13: 0.08 | E13: 0.76861397 | F13: 0.25
A14: Base | B14: 35.174192 | C14: 0.01337345 | D14: 0.11 | E14: 0.79466275 | F14: 0.5
A15: Upside | B15: 44.770151 | C15: 0.28983436 | D15: 0.135 | E15: 0.80973486 | F15: 0.25
A16: Probability-weighted value | B16: 34.812643 | C16: 0.0029571543
A18: Break-even: base-case FY2031 EBIT margin needed for $34.71 is about 11% (the base case); each 1 pt of FY2031 EBIT margin is worth about $3 per share.

Sheet Football Field
A1: Valuation summary - value per share ($)
A3: Method | B3: Low | C3: High | D3: Midpoint
A4: 52-week trading range | B4: 31.97 | C4: 70.44 | D4: =AVERAGE(B4:C4) -> 51.205
A5: DCF: downside to upside scenarios | B5: 24.132036 | C5: 44.770151 | D5: =AVERAGE(B5:C5) -> 34.451093
A6: Comps: EV/EBITDA 25th-75th pct (FY2026 EBITDA) | B6: =Comps!D22 -> 28.422341 | C6: =Comps!F22 -> 50.512935 | D6: =AVERAGE(B6:C6) -> 39.467638
A8: Current price | B8: =Assumptions!B5 -> 34.71
A9: DCF base case (live; follows scenario switch) | B9: =DCF!B29 -> 35.174192
